[
  {
    "username": "yusril-adr",
    "desc": "FrontEnd and BackEnd JS Developer"
  },
  {
    "username": "TeddyFirman",
    "desc": "Machine Learning Enthusiast | Python | BackEnd Tech"
  },
  {
    "username": "iyakiwan",
    "desc": "Android Developer | iOS Developer | Google Certified - Associate Android Developer"
  },
  {
    "username": "putrasena21",
    "desc": "Backend Javascript Developer"
  },
  {
    "username": "adhipramanax",
    "desc": "FrontEnd Web Developer"
  },
  {
    "username": "anmistrz",
    "desc": "FrontEnd Web Developer | UI/UX Designer "
  }
]
